MANIFEST.in
README.md
setup.py
virustotal2.py
virustotal2.egg-info/PKG-INFO
virustotal2.egg-info/SOURCES.txt
virustotal2.egg-info/dependency_links.txt
virustotal2.egg-info/top_level.txt