Metadata-Version: 1.1
Name: virustotal2
Version: 1.1
Summary: Complete, Pythonic VirusTotal Public API 2.0 client
Home-page: https://github.com/Phillipmartin/virustotal2
Author: Philip Martin
Author-email: phillip.martin@gmail.com
License: MIT
Platform: UNKNOWN
Classifier: Development Status :: 4 - Beta
Classifier: Environment :: Console
Classifier: Intended Audience :: Developers
Classifier: Intended Audience :: System Administrators
Classifier: License :: OSI Approved :: MIT License
Classifier: Programming Language :: Python
Classifier: Topic :: Security
Classifier: Topic :: Software Development :: Libraries :: Python Modules
Requires: requests
